finscraper/__init__.py
finscraper/_version.py
finscraper/extensions.py
finscraper/middlewares.py
finscraper/pipelines.py
finscraper/request.py
finscraper/settings.py
finscraper/spiders.py
finscraper/text_utils.py
finscraper/utils.py
finscraper/wrappers.py
finscraper/scrapy_spiders/__init__.py
finscraper/scrapy_spiders/ilarticle.py
finscraper/scrapy_spiders/isarticle.py
finscraper/scrapy_spiders/mixins.py
finscraper/scrapy_spiders/mnetpage.py
finscraper/scrapy_spiders/oikotieapartment.py
finscraper/scrapy_spiders/suomi24page.py
finscraper/scrapy_spiders/torideal.py
finscraper/scrapy_spiders/vauvapage.py
finscraper/scrapy_spiders/ylearticle.py
finscraper-0.2.5.dist-info/LICENSE
finscraper-0.2.5.dist-info/METADATA
finscraper-0.2.5.dist-info/WHEEL
finscraper-0.2.5.dist-info/top_level.txt
finscraper-0.2.5.dist-info/RECORD
