Metadata-Version: 2.1
Name: finscraper
Version: 0.2.5
Summary: Web scraping API for Finnish websites
Author-email: Jesse Myrberg <jesse.myrberg@gmail.com>
License: MIT License
Project-URL: Homepage, https://github.com/jmyrberg/finscraper
Project-URL: Documentation, https://finscraper.readthedocs.io
Keywords: web,scraping,finnish,nlp,scrapy
Classifier: Development Status :: 4 - Beta
Classifier: Programming Language :: Python :: 3
Classifier: Framework :: Scrapy
Classifier: Natural Language :: Finnish
Classifier: Intended Audience :: Developers
Classifier: License :: OSI Approved :: MIT License
Requires-Python: >=3.8
License-File: LICENSE
Requires-Dist: attrs >=21
Requires-Dist: pandas >=1
Requires-Dist: selenium >=4
Requires-Dist: scrapy >=2.6.3
Requires-Dist: tqdm >=4.46
Requires-Dist: webdriver-manager >=2.4
Provides-Extra: dev
Requires-Dist: pytest ; extra == 'dev'
Requires-Dist: flake8 ; extra == 'dev'
Requires-Dist: twine ; extra == 'dev'
Requires-Dist: versioneer ; extra == 'dev'
